agentcube/__init__.py
agentcube/cli/__init__.py
agentcube/cli/main.py
agentcube/operations/__init__.py
agentcube/runtime/__init__.py
agentcube/runtime/build_runtime.py
agentcube/runtime/invoke_runtime.py
agentcube/runtime/pack_runtime.py
agentcube/runtime/publish_runtime.py
agentcube/runtime/status_runtime.py
agentcube/services/__init__.py
agentcube/services/agentcube_provider.py
agentcube/services/docker_service.py
agentcube/services/k8s_provider.py
agentcube/services/metadata_service.py
agentcube_cli-0.2.0.dist-info/METADATA
agentcube_cli-0.2.0.dist-info/WHEEL
agentcube_cli-0.2.0.dist-info/entry_points.txt
agentcube_cli-0.2.0.dist-info/top_level.txt
agentcube_cli-0.2.0.dist-info/RECORD
