Metadata-Version: 2.4
Name: agentcube-cli
Version: 0.2.0
Summary: AgentCube CLI - A developer tool for packaging, building, and deploying AI agents to AgentCube
License: Apache-2.0
Project-URL: Homepage, https://github.com/volcano-sh/agentcube
Project-URL: Documentation, https://agentcube.readthedocs.io/
Project-URL: Repository, https://github.com/volcano-sh/agentcube/tree/main/cmd/cli
Project-URL: Issues, https://github.com/volcano-sh/agentcube/issues
Keywords: ai,agent,kubernetes,volcano,agentcube,cli
Classifier: Development Status :: 3 - Alpha
Classifier: Intended Audience :: Developers
Classifier: License :: OSI Approved :: Apache Software License
Classifier: Programming Language :: Python :: 3
Classifier: Programming Language :: Python :: 3.8
Classifier: Programming Language :: Python :: 3.9
Classifier: Programming Language :: Python :: 3.10
Classifier: Programming Language :: Python :: 3.11
Classifier: Programming Language :: Python :: 3.12
Classifier: Topic :: Software Development :: Libraries :: Python Modules
Classifier: Topic :: System :: Systems Administration
Classifier: Topic :: Internet :: WWW/HTTP :: Dynamic Content
Requires-Python: >=3.8
Requires-Dist: typer[all]>=0.9.0
Requires-Dist: pydantic>=2.0.0
Requires-Dist: pyyaml>=6.0
Requires-Dist: httpx>=0.24.0
Requires-Dist: docker>=6.0.0
Requires-Dist: rich>=13.0.0
Requires-Dist: packaging>=23.0
Requires-Dist: importlib-resources>=6.0.0
Requires-Dist: semver>=3.0.0
Provides-Extra: k8s
Requires-Dist: kubernetes>=28.0.0; extra == "k8s"
Provides-Extra: dev
Requires-Dist: pytest>=7.4.0; extra == "dev"
Requires-Dist: pytest-asyncio>=0.21.0; extra == "dev"
Requires-Dist: pytest-cov>=4.1.0; extra == "dev"
Requires-Dist: black>=23.0.0; extra == "dev"
Requires-Dist: isort>=5.12.0; extra == "dev"
Requires-Dist: flake8>=6.0.0; extra == "dev"
Requires-Dist: mypy>=1.5.0; extra == "dev"
Requires-Dist: pre-commit>=3.3.0; extra == "dev"
Requires-Dist: kubernetes>=28.0.0; extra == "dev"
Provides-Extra: test
Requires-Dist: pytest>=7.4.0; extra == "test"
Requires-Dist: pytest-asyncio>=0.21.0; extra == "test"
Requires-Dist: pytest-cov>=4.1.0; extra == "test"
Requires-Dist: pytest-mock>=3.11.0; extra == "test"
Requires-Dist: httpx-mock>=0.10.0; extra == "test"
